setup.py
nanoweb/__init__.py
nanoweb.egg-info/PKG-INFO
nanoweb.egg-info/SOURCES.txt
nanoweb.egg-info/dependency_links.txt
nanoweb.egg-info/entry_points.txt
nanoweb.egg-info/not-zip-safe
nanoweb.egg-info/requires.txt
nanoweb.egg-info/top_level.txt