Metadata-Version: 1.0
Name: nanoweb
Version: 1.0
Summary: The nano web framework
Home-page: http://eric.themoritzfamily.com
Author: Eric Moritz
Author-email: eric@themoritzfamily.com
License: BSD
Keywords: WSGI
Platform: UNKNOWN
